omniart_eye_classifier/__init__.py
omniart_eye_classifier/classifier_model.py
omniart_eye_classifier/classifier_model_state.pth
omniart_eye_classifier/classify_eye.py
omniart_eye_classifier-0.1.3.dist-info/METADATA
omniart_eye_classifier-0.1.3.dist-info/WHEEL
omniart_eye_classifier-0.1.3.dist-info/top_level.txt
omniart_eye_classifier-0.1.3.dist-info/RECORD
