Metadata-Version: 2.1
Name: omniart-eye-classifier
Version: 0.1.3
Summary: A CNN that can classify eyes by their respective colour
Home-page: http://github.com/rogierknoester/omniart_eye_classifier
Author: Rogier Knoester
Author-email: knoesterrogier+omniart@gmail.com
License: MIT
Platform: UNKNOWN
